{
	"format_version": "1.8.0",
	"minecraft:client_entity": {
		"description": {
			"identifier": "pa:anomalocaris",
			"materials": {
				"default": "entity_alphatest"
			},
			"textures": {
				"default": "textures/entity/anomalocaris"
			},
			"geometry": {
				"default": "geometry.anomalocaris"
			},
			"animations": {
				"move": "animation.anomalocaris.move"
			},
			"animation_controllers": [
				{
					"move": "controller.animation.silverfish.move"
				}
			],
			"render_controllers": ["controller.render.default"],
			"spawn_egg": {
				"base_color": "#76492b",
				"overlay_color": "#9fb0f5"
			}
		}
	}
}