{
    "format_version": "1.10.0",
    "minecraft:client_entity": {
      "description": {
        "identifier": "jctstatues:endermanstatue4",
        "materials": { "default": "bat" },
        "textures": {
          "default": "textures/entity/endermanstatue4"
        },
        "geometry": {
          "default": "geometry.endermanstatue1"
        },
        "render_controllers": [ "controller.render.statue" ],
        "spawn_egg": {
          "texture": "endermanstatue4item"
        }
      }
    }
  }
  