{
	"file_path": "C:\\Users\\239168\\AppData\\Local\\Packages\\Microsoft.MinecraftUWP_8wekyb3d8bbwe\\LocalState\\games\\com.mojang\\development_behavior_packs\\Biome Revamp DAT\\features\\weighted_random_chalkstone_curves_feature.json",
	"file_type": "feature",
	"format_version": 1,
	"file_uuid": "928a6226_f666_4adb_9780_3e2f1074063c",
	"file_version": 5,
	"cache_content": {
		"children": [
			{
				"data": "1.17.0",
				"key": "format_version"
			},
			{
				"open": {
					"format_version": "1.17.0",
					"minecraft:weighted_random_feature": {
						"description": {
							"identifier": "mv:weighted_random_chalkstone_curves_feature"
						},
						"features": [
							[
								"mv:chalkstone_pillar1_feature",
								1
							],
							[
								"mv:chalkstone_pillar4_feature",
								1
							]
						]
					}
				},
				"key": "minecraft:weighted_random_feature",
				"children": [
					{
						"open": {
							"description": {
								"identifier": "mv:weighted_random_chalkstone_curves_feature"
							},
							"features": [
								[
									"mv:chalkstone_pillar1_feature",
									1
								],
								[
									"mv:chalkstone_pillar4_feature",
									1
								]
							]
						},
						"key": "description",
						"is_minified": true,
						"children": {
							"identifier": "mv:weighted_random_chalkstone_curves_feature"
						}
					},
					{
						"open": {
							"description": {
								"identifier": "mv:weighted_random_chalkstone_curves_feature"
							},
							"features": [
								[
									"mv:chalkstone_pillar1_feature",
									1
								],
								[
									"mv:chalkstone_pillar4_feature",
									1
								]
							]
						},
						"key": "features",
						"children": [
							{
								"open": [
									[
										"mv:chalkstone_pillar1_feature",
										1
									],
									[
										"mv:chalkstone_pillar4_feature",
										1
									]
								],
								"is_minified": true,
								"children": [
									"mv:chalkstone_pillar1_feature",
									1
								]
							},
							{
								"open": [
									[
										"mv:chalkstone_pillar1_feature",
										1
									],
									[
										"mv:chalkstone_pillar4_feature",
										1
									]
								],
								"is_minified": true,
								"children": [
									"mv:chalkstone_pillar4_feature",
									1
								]
							}
						]
					}
				]
			}
		]
	}
}