{
	"format_version": "1.12.0",
	"minecraft:geometry": [
		{
			"description": {
				"identifier": "geometry.nautilus_block",
				"texture_width": 32,
				"texture_height": 16,
				"visible_bounds_width": 3,
				"visible_bounds_height": 2.5,
				"visible_bounds_offset": [0, 0.75, 0]
			},
			"bones": [
				{
					"name": "bose",
					"pivot": [0, 0, 0],
					"rotation": [0, -90, 0],
					"cubes": [
						{"origin": [-2.5, -3, -3.5], "size": [7, 7, 7], "pivot": [0, 0, 0], "rotation": [-109, -26, 95], "uv": [0, 0]}
					]
				}
			]
		}
	]
}